jupsolhelp/__init__.py
jupsolhelp/helper.py
jupsolhelp-0.1.2.dist-info/METADATA
jupsolhelp-0.1.2.dist-info/WHEEL
jupsolhelp-0.1.2.dist-info/entry_points.txt
jupsolhelp-0.1.2.dist-info/top_level.txt
jupsolhelp-0.1.2.dist-info/RECORD
