Metadata-Version: 2.1
Name: jupsolhelp
Version: 0.1.2
Requires-Dist: requests
